{"Services":[
  {
    "id":1,
    "name":"Sesiones de Reiki",
    "photo":"src//assets//serviceimg//Reiki.jpg",
    "desc":"Canalizamos la energia universal para curar las dolencias emocionales, psicologicas y fisicas de nuestros pacientes.",
    "link":"",
    "timeTable": "Reservar Cita"
},
{
  "id":2,
  "name":"Clases de Yoga",
  "photo":"src//assets//serviceimg//yoga.jpg",
  "desc":"Con posturas ancestrales, elongamos y fortalecemos nuestro cuerpo, para llevar una vida mas sana con el.",
  "link":"",
  "timeTable": "Lu a Vie 10:30 Am a 11:30 Am  y  18:30 Pm a 19:30 Pm"
},
{
  "id":3,
  "name":"Meditacion Grupal",
  "photo":"src//assets//serviceimg//meditacion.jpg",
  "desc":"Llevamos a cabo meditaciones guiadas para buscar dentro nuestro las respuestas que nos llevaran a tener una mejor convivencia con nosotros mismos.",
  "link":"",
  "timeTable": "Lu a Vie 9:00 Am a 10:00 Am  y  19:40 Pm a 20:40 Pm"
},
{
    "id":4,
    "name":"Lectura de Carta Astral",
    "photo":"src//assets//serviceimg//cartaastral.jpg",
    "desc":"Leemos como se encontraban los astros el dia de tu nacimiento, asi sabemos hacia donde nos guian.",
    "link":"",
    "timeTable": "Reservar Cita"
},
{
  "id":5,
  "name":"Sesiones de Masajes",
  "photo":"src//assets//serviceimg//masajes.jpg",
  "desc":"Sesiones de 15, 30 o 60 minutos de masages descontracturantes y quiropracticos.",
  "link":"",
  "timeTable": "Reservar Cita"
}]
}